lib/libnvqir-Qleo.so
lib/libnvqir-QleoGPU.so
qleo/__init__.py
qleo/visualization/__init__.py
qleo-0.22.6.data/data/lib/python3.10/site-packages/lib/libnvqir-Qleo.so
qleo-0.22.6.data/data/lib/python3.10/site-packages/lib/libnvqir-QleoGPU.so
qleo-0.22.6.data/data/lib/python3.10/site-packages/targets/Qleo.yml
qleo-0.22.6.data/data/lib/python3.10/site-packages/targets/QleoGPU.yml
qleo-0.22.6.dist-info/licenses/LICENSE
targets/Qleo.yml
targets/QleoGPU.yml
qleo-0.22.6.dist-info/METADATA
qleo-0.22.6.dist-info/WHEEL
qleo-0.22.6.dist-info/top_level.txt
qleo-0.22.6.dist-info/RECORD
