Metadata-Version: 2.4
Name: qleo
Version: 0.22.6
Summary: Quobly Logical Emulator Online
Author-email: QPerfect <guido.masella@qperfect.io>
License-Expression: Apache-2.0
Project-URL: Homepage, https://github.com/qperfect-io/qleo
Project-URL: Documentation, https://docs.qperfect.io/qleo
Project-URL: Repository, https://github.com/qperfect-io/qleo
Project-URL: Issues, https://github.com/qperfect-io/qleo/issues
Requires-Python: <4,>=3.9
License-File: LICENSE
Requires-Dist: quantanium<2.0.0,>=1.0.12
Provides-Extra: visualization
Requires-Dist: matplotlib<4,>=3.8; extra == "visualization"
Provides-Extra: cudaq
Requires-Dist: cudaq<1; extra == "cudaq"
Dynamic: license-file
